imgaugtf/__init__.py
imgaugtf/augmentations.py
imgaugtf/batch_augmentations.py
imgaugtf/functional.py
imgaugtf/utils.py
imgaugtf/seg/__init__.py
imgaugtf/seg/augmentations.py
imgaugtf/seg/batch_augmentations.py
imgaugtf/seg/utils.py
imgaugtf-1.0.0.dist-info/LICENSE
imgaugtf-1.0.0.dist-info/METADATA
imgaugtf-1.0.0.dist-info/WHEEL
imgaugtf-1.0.0.dist-info/top_level.txt
imgaugtf-1.0.0.dist-info/RECORD
