Metadata-Version: 2.1
Name: imgaugtf
Version: 1.0.0
Summary: tensorflow native image augmantation
Home-page: https://github.com/hirune924/imgaug-tf/
Author: hirune924
License: Apache License Version 2.0
Platform: UNKNOWN
Requires-Dist: tensorflow (>=2.0)
Requires-Dist: tensorflow-addons (>=0.7.1)
Requires-Dist: tensorflow-probability (>=0.7.1)
